{
  "APP_NAME": "ngX-Rocket French",
  "About": "A propos",
  "Hello world !": "Bonjour le monde !",
  "Home": "Accueil",
  "Email address": "Adresse e-mail",
  "We ll never share your email with anyone else.": "Nous ne partagerons jamais votre e-mail avec quelqu'un d'autre.",
  "Check me out": "Vérifiez-moi",
  "Submit": "Soumettre",
  "Logged in as": "Connecté en tant que",
  "Login": "Connexion",
  "Sign In": "S'identifier",
  "Dont have an account?": "Vous n'avez pas de compte ?",
  "Create new": "Créer un nouveau",
  "Please Sign in": "Veuillez vous connecter",
  "Please Sign Up": "Inscrivez vous s'il vous plait",
  "First Name": "Prénom",
  "Last Name": "Nom de famille",
  "Logout": "Déconnexion",
  "Sign up": "S'inscrire",
  "Password": "Mot de passe",
  "Reset Password": "réinitialiser le mot de passe",
  "Reset": "Réinitialiser",
  "Cancel": "Annuler",
  "Set New Password": "Definir un nouveau mot de passe",
  "Change Password": "Changer le mot de passe",
  "Clear": "Dégager",
  "Already have an account?": "Vous avez déjà un compte?",
  "Password is required": "Mot de passe requis",
  "Username": "Identifiant",
  "Username is required": "Identifiant requis",
  "Username or password incorrect.": "Identifiant ou mot de passe incorrect.",
  "Remember me": "Rester connecté",
  "Version": "Version"
}
